PyPoli/Hello.py
PyPoli/LT.py
PyPoli/Poli.py
PyPoli/Time.py
PyPoli/__init__.py
PyPoli/baid_dr.py
PyPoli/bot.py
PyPoli/calculation.py
PyPoli/chp.py
PyPoli/djt.py
PyPoli/fy.py
PyPoli/gen.py
PyPoli/jr_jr.py
PyPoli/kgmv.py
PyPoli/lishi.py
PyPoli/open_url_exe.py
PyPoli/play.py
PyPoli/qq_JZ.py
PyPoli/qq_tx_mz.py
PyPoli/rkl.py
PyPoli/sao_hua.py
PyPoli/sj_pz.py
PyPoli/sjyy.py
PyPoli/tgrj.py
PyPoli/tl_api.py
PyPoli/twqh.py
PyPoli/weather_api.py
PyPoli/xh.py
PyPoli/yq.py
PyPoli-0.1.0.dist-info/LICENSE.txt
PyPoli-0.1.0.dist-info/METADATA
PyPoli-0.1.0.dist-info/WHEEL
PyPoli-0.1.0.dist-info/top_level.txt
PyPoli-0.1.0.dist-info/RECORD
