Metadata-Version: 2.1
Name: PyPoli
Version: 0.1.0
Summary: 机器人|robot
Home-page: https://codechina.csdn.net/qq_53280175/polirobt
Author: PYmili
Author-email: mc2005wj@163.com
Maintainer: PYmili
Maintainer-email: mc2005wj@163.com
License: MIT License
Platform: UNKNOWN
Classifier: Operating System :: OS Independent
Classifier: Natural Language :: Chinese (Simplified)
Classifier: License :: OSI Approved :: MIT License
Classifier: Programming Language :: Python :: 3.7
Classifier: Programming Language :: Python :: 3.8
Classifier: Programming Language :: Python :: 3.9
Classifier: Topic :: Software Development :: Libraries
Requires-Python: >=3.8
License-File: LICENSE.txt
Requires-Dist: baidu-api (>=0.0.2)
Requires-Dist: RandomKey (>=0.0.1)
Requires-Dist: FastDataTime (>=0.0.8)
Requires-Dist: bs4 (>=0.0.1)
